arrex/__init__.py
arrex/dtypes.c
arrex/dtypes.cp39-win_amd64.pyd
arrex/dtypes.pxd
arrex/dtypes.pyx
arrex/glm.py
arrex/list.c
arrex/list.cp39-win_amd64.pyd
arrex/list.pyx
arrex/numbers.c
arrex/numbers.cp39-win_amd64.pyd
arrex/numbers.pyx
arrex/numpy.py
arrex-0.5.0.dist-info/COPYING
arrex-0.5.0.dist-info/COPYING.LESSER
arrex-0.5.0.dist-info/METADATA
arrex-0.5.0.dist-info/WHEEL
arrex-0.5.0.dist-info/top_level.txt
arrex-0.5.0.dist-info/RECORD
