Metadata-Version: 2.1
Name: arrex
Version: 0.5.0
Summary: typed arrays using any custom type as element type
Home-page: https://github.com/jimy-byerley/arrex
Author: Jimy Byerley
Author-email: jimy.byerley@gmail.com
License: GNU LGPL v3
Keywords: buffer array list dynamic dtype serialization numeric
Platform: UNKNOWN
Classifier: License :: OSI Approved :: GNU General Public License v3 or later (GPLv3+)
Classifier: Development Status :: 3 - Alpha
Classifier: Programming Language :: Python :: 3.8
Classifier: Programming Language :: Python :: 3.9
Classifier: Programming Language :: Python :: 3.10
Classifier: Topic :: Software Development :: Libraries
Classifier: Topic :: Utilities
Requires-Python: >=3.8
